src/__init__.py
src/main.py
tests/__init__.py
heatwave-1.2.0.dist-info/LICENSE
heatwave-1.2.0.dist-info/METADATA
heatwave-1.2.0.dist-info/WHEEL
heatwave-1.2.0.dist-info/entry_points.txt
heatwave-1.2.0.dist-info/top_level.txt
heatwave-1.2.0.dist-info/RECORD
