Metadata-Version: 2.1
Name: heatwave
Version: 1.2.0
Summary: A way of visualizing a heat map of a git repo
Home-page: https://github.com/james-stoup/heatwave
Author: James Stoup
Author-email: james.r.stoup@gmail.com
License: GNU General Public License v3.0
Keywords: git visualize heatmap
Platform: UNKNOWN
Requires-Python: >=3.7
Requires-Dist: Click
Requires-Dist: MonthDelta
Requires-Dist: GitPython
